geometry_utils/__init__.py
geometry_utils/bidimensional.py
geometry_utils/helper.py
geometry_utils/tridimensional.py
geometry_utils-0.1.3.dist-info/LICENSE
geometry_utils-0.1.3.dist-info/METADATA
geometry_utils-0.1.3.dist-info/WHEEL
geometry_utils-0.1.3.dist-info/top_level.txt
geometry_utils-0.1.3.dist-info/RECORD
