Metadata-Version: 2.1
Name: geometry-utils
Version: 0.1.3
Summary: A collection of functions for bidimensional and tridimensional arithmetic geometry.
Home-page: https://github.com/ihavenonickname/geometry-utils
Author: Gabriel Blank Stift Mousquer
Author-email: gabrielblanksm@gmail.com
License: MIT
Platform: UNKNOWN
